condy/__init__.py
condy/client.py
condy/config.py
condy/exceptions.py
condy/models.py
condy/utils.py
condy-0.3.9.dist-info/METADATA
condy-0.3.9.dist-info/WHEEL
condy-0.3.9.dist-info/RECORD
